setup.py
weighwords/__init__.py
weighwords/logsum.py
weighwords.egg-info/PKG-INFO
weighwords.egg-info/SOURCES.txt
weighwords.egg-info/dependency_links.txt
weighwords.egg-info/requires.txt
weighwords.egg-info/top_level.txt