Metadata-Version: 1.0
Name: weighwords
Version: 0.2
Summary: Python library for creating word weights/word clouds from text
Home-page: UNKNOWN
Author: Lars Buitinck
Author-email: L.J.Buitinck@uva.nl
License: LGPL
Keywords: word cloud nlp language model
Platform: UNKNOWN
Classifier: Development Status :: 4 - Beta
Classifier: License :: OSI Approved :: GNU Library or Lesser General Public License (LGPL)
Classifier: Topic :: Text Processing
